{
    "id": "ID_c5024492-a23e-4d56-98b3-8c15cf843393",
    "text": "Loss of taste",
    "engineVersion": "3.0",
    "display-mr": "चव जाणे",
    "display-hi": "स्वाद के ज्ञान में कमी",
    "options": [
        {
            "id": "ID_73c897bc-580f-4373-9e84-0bfeb41efaf3",
            "text": "Since when have you had loss of taste?",
            "display-mr": "तुमच्या तोंडाची चव कधीपासून गेली आहे?",
            "display-hi": "आपको स्वाद महसूस न करने की समस्या कब से है?",
            "isRequired": true,
            "multi-choice": false,
            "options": [
                {
                    "id": "ID_f6f52826-ce74-4295-9158-8bac2d831f7f",
                    "text": "Since when have you had loss of taste?",
                    "display-mr": "तुमच्या तोंडाची चव कधीपासून गेली आहे?",
                    "display-hi": "आपको स्वाद महसूस न करने की समस्या कब से है?",
                    "input-type": "duration"
                }
            ]
        },
        {
            "id": "ID_a8e1b124-8d33-4292-a627-f150e25e6704",
            "text": "How fast did loss of taste develop?",
            "display-mr": "तोंडोची चव कधीपासून गेली आहे?",
            "display-hi": "स्वाद महसूस न कर पाने की समस्या कितनी तेजी से बढ़ी है?",
            "isRequired": true,
            "multi-choice": false,
            "options": [
                {
                    "id": "ID_9743541b-7078-4c06-92b3-a7e73e4d80ff",
                    "text": "Suddenly",
                    "display-mr": "अचानक",
                    "display-hi": "अचानक"
                },
                {
                    "id": "ID_fcd819bb-62c4-49b4-a97f-f754c098213d",
                    "text": "Slowly",
                    "display-mr": "हळूहळू",
                    "display-hi": "धीरे-धीरे"
                }
            ]
        },
        {
            "id": "ID_204e8952-917c-49f7-b078-b984542dcc80",
            "text": "Do you have the following features associated with loss of taste?",
            "display-mr": "तुम्हाला खालील लक्षणे आहेत का?",
            "display-hi": "क्या आपको स्वाद में कमी की समस्या से जुड़ी निम्नलिखित विशेषताएं हैं?",
            "isRequired": true,
            "multi-choice": true,
            "options": [
                {
                    "id": "ID_603c4b72-4a99-4688-bca4-3561d975b1a5",
                    "text": "None",
                    "display-mr": "काहीही नाही",
                    "display-hi": "कोई नहीं",
                    "exclude-from-multi-choice": "true"
                },
                {
                    "id": "ID_37e868b0-702b-4c75-8b4d-f317dc430835",
                    "text": "Loss of smell",
                    "display-mr": "चव जाणे",
                    "display-hi": "गंध महसूस न कर पाना"
                },
                {
                    "id": "ID_bf7aec67-da1e-4c4c-9b21-7564a9ee37fa",
                    "text": "Redness of tongue",
                    "display-mr": "जीभ लालसर होणे",
                    "display-hi": "जीभ का लाल होना"
                },
                {
                    "id": "ID_4736de64-8820-4fff-a563-bfac9fc84d55",
                    "text": "Coating of tongue",
                    "display-mr": "जिभेवर थर चढणे",
                    "display-hi": "जीभ पर परत जमना"
                },
                {
                    "id": "ID_11c4049f-e563-495f-be7c-4b432f75506b",
                    "text": "Nasal discharge",
                    "display-mr": "नाकातून पाणी येणे",
                    "display-hi": "नाक से स्राव"
                },
                {
                    "id": "ID_537d3d3e-d50a-444d-988c-19fad54be0bf",
                    "text": "Sneezing",
                    "display-mr": "शिंकणे",
                    "display-hi": "छींकना"
                },
                {
                    "id": "ID_a06128ea-6620-4cca-b95a-d4995ba38790",
                    "text": "Dry mouth",
                    "display-mr": "तोंड कोरडे पडणे",
                    "display-hi": "मुंह सूखना"
                },
                {
                    "id": "ID_0195980d-aafd-475b-9889-bab2fad8cef7",
                    "text": "Other",
                    "display-mr": "अन्य",
                    "display-hi": "अन्य",
                    "input-type": "text"
                }
            ]
        },
        {
            "id": "ID_8b414605-a0de-40a5-b0cd-f4b1de27fb50",
            "text": "How is loss of taste problem progressing?",
            "display-mr": "चव न लागण्याची समस्या कशी आहे?",
            "display-hi": "स्वाद महसूस न कर पाने की समस्या में कुछ बदलाव है क्या?",
            "isRequired": true,
            "multi-choice": false,
            "options": [
                {
                    "id": "ID_e6832297-5fbe-47a0-8317-a1bdaab18d81",
                    "text": "Increasing",
                    "display-mr": "वाढत आहे",
                    "display-hi": "बढ़ता हुआ"
                },
                {
                    "id": "ID_ba8d2f48-6061-4278-9abe-070d42051d30",
                    "text": "Decreasing",
                    "display-mr": "कमी होत आहे",
                    "display-hi": "घटता हुआ"
                },
                {
                    "id": "ID_df486246-9b9e-4b01-bc36-c465b1a2e530",
                    "text": "Recurrent",
                    "display-mr": "वारंवार",
                    "display-hi": "बार-बार होना"
                },
                {
                    "id": "ID_b768a8a9-f898-46c2-bb1d-5e03668ec0d5",
                    "text": "No change",
                    "display-mr": "काही बदल नाही",
                    "display-hi": "कोई बदलाव नहीं"
                }
            ]
        },
        {
            "id": "ID_fc543a84-897f-4523-83b5-d588e6244033",
            "text": "Associated symptoms",
            "display-mr": "तुम्हाला खालील लक्षणे आहेत का?",
            "display-hi": "क्या आपको निम्नलिखित लक्षण हैं?",
            "isRequired": true,
            "options": [
                {
                    "id": "ID_46277320-7d8e-48fc-9203-5af8e9600035",
                    "text": "Loss of appetite",
                    "display-mr": "भूक न लागणे",
                    "display-hi": "भूख न लगना"
                },
                {
                    "id": "ID_d8255db1-2fda-45e5-9e99-e35b3e1af0c6",
                    "text": "Facial pain",
                    "display-mr": "चेहरा दुखणे",
                    "display-hi": "चेहरे में दर्द"
                },
                {
                    "id": "ID_8f188317-cc4f-441d-9121-df64668b7d00",
                    "text": "Throat pain",
                    "display-mr": "घसादुखी",
                    "display-hi": "गले में दर्द"
                },
                {
                    "id": "ID_f07d05a0-1e76-4260-aead-e25a5d0ef849",
                    "text": "Deviation of mouth",
                    "display-mr": "तोंड वाकडे होणे",
                    "display-hi": "मुंह का टेढ़ा होना"
                },
                {
                    "id": "ID_9bac262f-3cce-4546-9fd5-2f953554d8d5",
                    "text": "Drooling of saliva",
                    "display-mr": "लाळ गळणे",
                    "display-hi": "लार टपकना"
                },
                {
                    "id": "ID_a5d5ea36-760d-4cdc-b8d4-603012e32c65",
                    "text": "White patches of mouth",
                    "display-mr": "तोंडाला पांढरे चट्टे पडणे",
                    "display-hi": "मुंह पर सफेद धब्बे"
                },
                {
                    "id": "ID_a65363b8-21f4-4f83-9f20-f4fe2ef86658",
                    "text": "History of head injury",
                    "display-mr": "डोक्याला मार लागल्याचा/इजा झाल्याचा पूर्वइतिहास",
                    "display-hi": "सिर पर चोट लगने का इतिहास"
                },
                {
                    "id": "ID_d92e55a8-dd5f-4ecf-ad8b-b55f5f9f414d",
                    "text": "History of medication intake",
                    "display-mr": "औषधे घेतल्याचा पूर्वइतिहास",
                    "display-hi": "दवा के सेवन का इतिहास"
                },
                {
                    "id": "ID_389c3969-bef1-4e83-bed9-ef19efbe935c",
                    "text": "History of recent COVID-19 infection",
                    "display-mr": "नुकताच कोविड-19 चा संसर्ग झाल्याचा पूर्वइतिहास",
                    "display-hi": "हाल ही में कोविड-19 संक्रमण का इतिहास"
                }
            ],
            "display": "Do you have the following symptom(s)?"
        },
        {
            "id": "ID_0c332b49-18c3-419c-8d46-e6764478f76f",
            "text": "Do you have any other symptoms?",
            "display-mr": "तुम्हाला खालील लक्षणे आहेत का?",
            "display-hi": "क्या आपको निम्नलिखित लक्षण हैं?",
            "isRequired": true,
            "multi-choice": true,
            "options": [
                {
                    "id": "ID_509b398f-a548-4cd9-9ee6-5635c1fa7ead",
                    "text": "None",
                    "display-mr": "काही नाही",
                    "display-hi": "कोई नहीं",
                    "exclude-from-multi-choice": "true"
                },
                {
                    "id": "ID_6baf554f-a659-4d74-88c6-c6e021f5b86c",
                    "text": "Fever",
                    "display-mr": "ताप",
                    "display-hi": "बुखार"
                },
                {
                    "id": "ID_1342ee2b-561f-42ad-9355-86c720718a63",
                    "text": "Dizziness",
                    "display-mr": "चक्कर",
                    "display-hi": "चक्कर आना"
                },
                {
                    "id": "ID_8698dcf8-1ac5-445f-8130-ff7026d67fea",
                    "text": "Parotid swelling",
                    "display-mr": "पॅरोटीडला (कानाजवळील) ग्रंथीवर सूज",
                    "display-hi": "पैरोटिड ग्रेथि में सूजन"
                },
                {
                    "id": "ID_749b68f3-31a1-49db-a41c-6c7ef7c20693",
                    "text": "Headache",
                    "display-mr": "डोकेदुखी",
                    "display-hi": "सिरदर्द"
                },
                {
                    "id": "ID_96e7a0d9-7099-4ee6-ae85-bbcffda75a9f",
                    "text": "Muscle weakness",
                    "display-mr": "स्नायूंचा अशक्तपणा",
                    "display-hi": "मांसपेशियों में कमजोरी"
                },
                {
                    "id": "ID_d5bdc955-c616-4c50-9c68-0903eea40e46",
                    "text": "Pale skin",
                    "display-mr": "निस्तेज त्वचा",
                    "display-hi": "त्वचा का पीला पड़ना"
                },
                {
                    "id": "ID_7ea418f3-256a-4391-b2fc-896251f855bd",
                    "text": "Low mood",
                    "display-mr": "खराब मूड",
                    "display-hi": "उदासी"
                },
                {
                    "id": "ID_5bb6e6c4-22eb-4ad2-8f5b-4f22331a337f",
                    "text": "Fatigue",
                    "display-mr": "थकवा",
                    "display-hi": "थकान"
                },
                {
                    "id": "ID_756ca7bf-cea6-4887-af09-58a48edbf879",
                    "text": "Other",
                    "display-mr": "अन्य",
                    "display-hi": "अन्य",
                    "input-type": "text"
                }
            ]
        },
        {
            "id": "ID_1b3cd3c7-7c1d-4803-9ae2-1e04f57b07cd",
            "text": "Have you taken any treatment (including self-medication or home remedies) or seen any health provider for this problem?",
            "display-mr": "तुम्ही यासाठी कोणतेही उपचार (स्वत: घेतलेली किंवा घरगुती औषधे घेतली आहेत का किंवा या समस्येसाठी वैद्यकीय मदत घेतली आहे का?",
            "display-hi": "क्या आपने इस समस्या के लिए कोई उपचार (स्वयं दवाएं या घरेलू उपचार सहित) लिया है या किसी स्वास्थ्य प्रदाता से परामर्श किया है?",
            "isRequired": true,
            "multi-choice": false,
            "options": [
                {
                    "id": "ID_1501bac3-0215-4318-b398-73a96b25f247",
                    "text": "No",
                    "display-mr": "नाही",
                    "display-hi": "नहीं"
                },
                {
                    "id": "ID_16a4a707-ad92-4eff-ad61-2cf38f7ee99b",
                    "text": "Yes",
                    "display-mr": "होय",
                    "display-hi": "हां",
                    "options": [
                        {
                            "id": "ID_7bc1dea9-54b8-45d5-a624-e7295c3dc500",
                            "text": "Describe",
                            "display-mr": "वर्णन करा",
                            "display-hi": "वर्णन करें",
                            "isRequired": true,
                            "input-type": "text"
                        }
                    ]
                }
            ]
        },
        {
            "id": "ID_e5d27999-c789-4272-9556-83c7680ea90e",
            "text": "Additional Information",
            "display-mr": "अतिरिक्त माहिती",
            "display-hi": "अतिरिक्त जानकारी",
            "isRequired": true,
            "options": [
                {
                    "id": "ID_97de038b-d7ee-4c7f-8991-7b5a97d2f688",
                    "text": "[Enter additional information]",
                    "input-type": "text",
                    "language": "%",
                    "display-hi": "[अतिरिक्त जानकारी दर्ज करें]",
                    "display-mr": "[अजून काही माहिती असल्यास भरा]"
                }
            ]
        }
    ]
}